<?xml version="1.0" encoding="UTF-8"?>
<!--
  Licensed Materials - Property of IBM
 
  Copyright IBM Corporation 2012. All Rights Reserved.

  US Government Users Restricted Rights - Use, duplication or disclosure 
  restricted by GSA ADP Schedule Contract with IBM Corp.
-->
<!-- 
Copyright (c) 2006 , 2009 Curam Software Ltd.
All rights reserved.

This software is the confidential and proprietary information of Curam
Software, Ltd. ("Confidential Information").  You shall not
disclose such Confidential Information and shall use it only in accordance
with the terms of the license agreement you entered into with Curam Software.
-->
<messages package="curam.message">
  <message name="ERR_PLAN_GROUP_FV_NAME_BLANK">
    <locale language="ar">يجب ادخال اسم</locale>
  </message>
  <message name="ERR_PLAN_GROUP_XFV_NAME_EXISTS">
    <locale language="ar">لا يمكنك اضافة مجموعة الخطط هذه، حيث تم اضافة مجموعة خطة بهذا الاسم بالفعل الى قالب خطة الخدمة هذا.</locale>
  </message>
  <message name="ERR_PT_CREATE_PLAN_GROUP_FOR_CANCELED_TEMPLATE">
    <locale language="ar">لا يمكنك تكوين مجموعة خطة لقالب خطة تم الغاءه.</locale>
    <!-- BEGIN, CR00161962, LJ -->
    <!-- END, CR00161962 -->
  </message>
  <message name="ERR_PT_MODIFY_PLAN_GROUP_FOR_CANCELED_TEMPLATE">
    <locale language="ar">لا يمكنك تعديل مجموعة خطة لقالب خطة تم الغاءه.</locale>
    <!-- BEGIN, CR00161962, LJ -->
    <!-- END, CR00161962 -->
  </message>
  <message name="ERR_PT_PLANGROUP_DELETE_FROM_CANCELED_TEMPLATE">
    <locale language="ar">لا يمكن حذف مجموعة خطة لقالب الخطة من قالب خطة تم الغاءه.</locale>
    <!-- BEGIN, CR00161962, LJ -->
    <!-- END, CR00161962 -->
  </message>
</messages>

