<?xml version="1.0" encoding="UTF-8"?>
<!--
  Licensed Materials - Property of IBM
  
  PID 5725-H26
  
  Copyright IBM Corporation 2003, 2013. All rights reserved.
  
  US Government Users Restricted Rights - Use, duplication or disclosure
  restricted by GSA ADP Schedule Contract with IBM Corp.
-->
<!-- 
Copyright 2003-2005,2007,2009 Curam Software Ltd.
All rights reserved.

This software is the confidential and proprietary information of Curam
Software, Ltd. ("Confidential Information").  You shall not
disclose such Confidential Information and shall use it only in accordance
with the terms of the license agreement you entered into with Curam Software.
-->
<messages package="curam.message">
  <message name="ERR_WORK_QUEUE_FV_NAME_EMPTY">
    <locale language="ar">يجب ادخال اسم صف العمل.</locale>
  </message>
  <message name="ERR_WORK_QUEUE_FV_DUPLICATE_QUEUE_NAME">
    <locale language="ar">يوجد صف عمل بهذا الاسم بالفعل.</locale>
  </message>
  <message name="ERR_WORK_QUEUE_FV_ADMIN_USER_EMPTY">
    <locale language="ar">يجب تحديد موجه نظام لصف العمل.</locale>
  </message>
  <message name="ERR_WORK_QUEUE_XRV_SUBSCRIPTIONS_STILL_EXIST">
    <locale language="ar">لا يمكن حذف صف عمل اذا كان هناك مستخدمين مازال يتم اشتراكهم به.</locale>
  </message>
  <!-- BEGIN, CR00161962, KY -->
  <message name="ERR_WORK_QUEUE_XRV_ORG_SUBSCRIPTIONS_STILL_EXIST">
    <locale language="ar">لا يمكنك حذف صف عمل اذا كان هناك عناصر مؤسسة مازالت مشتركة به.</locale>
  </message>
  <!-- END, CR00161962 -->
  <message name="ERR_WORK_QUEUE_XRV_TASKS_STILL_EXIST">
    <locale language="ar">لا يمكن حذف صف عمل اذا كان هناك مهام مازالت مخصصة له.</locale>
  </message>
  <message name="ERR_WORK_QUEUE_XRV_CASE_OWNER">
    <locale language="ar">صف العمل هذا يعد مالك حالة واحدة أو أكثر لذلك لا يمكن الغاءه.</locale>
  </message>
  <message name="ERR_WORK_QUEUE_XRV_WORK_QUEUE_ADMIN_IS_CLOSED">
    <locale language="ar">لا يمكن اضافة مستخدم تم اغلاقه كموجه نظام في صف عمل.</locale>
  </message>
  <!-- Work Queue BOM Messages -->
  <message name="ERR_WORK_QUEUE_BOM_DOES_NOT_EXIST">
    <locale language="ar">نسخة BOM لصف العمل ذات كود التعريف "%1n" غير موجود.</locale>
    <cause>نسخة BOM لصف العمل المحدد غير موجودة بالنظام.</cause>
    <action>تأكد من أن كود تعريف صف العمل صحيح بالنسبة الى نسخة BOM لصف العمل الذي يتم تشغيله.</action>
  </message>
  <message name="INFO_ID_WORK_QUEUE_BUSINESS_OBJECT_INFORMATIONAL_NAME">
    <locale language="ar">صف العمل</locale>
    <cause>يستخدم بواسطة Informational BOM لصف العمل عند تكوين أداة التكوين.</cause>
    <action>هذا للأغراض الاعلامية فقط.</action>
  </message>
  <!-- End of Work Queue BOM Messages -->
  <!-- BEGIN, CR00388421, MV -->
  <message name="ERR_WORK_QUEUE_XFV_SPECIFY_SEARCH_CRITERIA">
    <locale language="ar">يجب أن تقوم بتحديد بعض معايير البحث.</locale>
  </message>
  <message name="INF_WORK_QUEUE_NO_MATCH_FOUND">
    <locale language="ar">لا توجد سجلات مطابقة محددة.</locale>
  </message>
  <!-- END, CR00388421 -->
</messages>

