<?xml version="1.0" encoding="UTF-8"?>
<!--
  Licensed Materials - Property of IBM
  
  Copyright IBM Corporation 2012. All Rights Reserved.
  
  US Government Users Restricted Rights - Use, duplication or disclosure 
  restricted by GSA ADP Schedule Contract with IBM Corp.
-->
<!-- 
    Copyright 2010 Curam Software Ltd.
    All rights reserved.
    
    This software is the confidential and proprietary information of Curam
    Software, Ltd. ("Confidential Information").  You shall not
    disclose such Confidential Information and shall use it only in accordance
    with the terms of the license agreement you entered into with Curam Software.
-->
<messages package="curam.message">
  <message name="ERR_FV_NAME_MUST_BE_ENTERED">
    <locale language="en">A name must be entered for the federal allowable component.</locale>
  </message>
  <message name="ERR_FV_COUNTABLE_TYPE_MUST_BE_ENTERED">
    <locale language="en">A countable type must be entered for the federal allowable component.</locale>
  </message>
  <message name="ERR_FV_START_DATE_MUST_BE_ENTERED">
    <locale language="en">A start date must be entered for the federal allowable component.</locale>
  </message>
  <message name="ERR_XFV_START_DATE_MUST_BE_EARLIER_THAN_END_DATE">
    <locale language="en">The start date must be earlier than the end date for the federal allowable component.</locale>
  </message>
  <message name="ERR_XFV_PROJECTION_AND_CA_CLIENT_PAID_STATUS_NOT_PAID">
    <locale language="en">The Projection Allowed indicator can only be selected if the Client Paid status is 'Paid'.</locale>
  </message>
  <message name="ERR_XRV_ACTIVITY_ALREADY_LINKED_TO_FEDERAL_COMPONENT">
    <locale language="en">The Federal Allowable Component, %1s, is already linked to this %2c.</locale>
  </message>
  <message name="ERR_XRV_NAME_MUST_BE_UNIQUE">
    <locale language="en">The Federal Allowable Component, %1s, already exists.</locale>
  </message>
  <message name="ERR_FV_RELATED_ID_MUST_BE_ENTERED">
    <locale language="en">You must select the service to be added to this federal allowable component.</locale>
  </message>
  <message name="ERR_FV_RELATED_TYPE_MUST_BE_ENTERED">
    <locale language="en">A related type must be set for the linked related record for the federal allowable component link.</locale>
  </message>
  <message name="ERR_FV_FEDERAL_ALLOWABLE_COMPONENT_MUST_BE_ENTERED">
    <locale language="en">A federal allowable component must be set for the federal allowable component link.</locale>
  </message>
  <message name="ERR_FV_FEDERAL_ALLOWABLE_COMPONENT_END_DATED_CANNOT_LINK">
    <locale language="en">The activity cannot be linked to the %1s federal allowable component, as it has an end date in the past.</locale>
  </message>
  <message name="ERR_FV_FEDERAL_ALLOWABLE_COMPONENT_CANCELLED_CANNOT_LINK">
    <locale language="en">The %1s federal allowable component is in a 'Cancelled' state, an activity cannot be linked to a federal allowable component in a 'Cancelled' state.</locale>
  </message>
  <message name="ERR_FV_SELECT_AT_LEAST_ONE_RELATED">
    <locale language="en">At least one %1c must be selected.</locale>
  </message>
</messages>
